wattrex_mn_manager/__init__.py
wattrex_mn_manager/__version__.py
wattrex_mn_manager/mn_broker_client.py
wattrex_mn_manager/mn_db_facade.py
wattrex_mn_manager/mn_manager_node.py
wattrex_mn_manager-1.0.9.dist-info/LICENSE.txt
wattrex_mn_manager-1.0.9.dist-info/METADATA
wattrex_mn_manager-1.0.9.dist-info/WHEEL
wattrex_mn_manager-1.0.9.dist-info/top_level.txt
wattrex_mn_manager-1.0.9.dist-info/RECORD
