Metadata-Version: 2.1
Name: wattrex-mn-manager
Version: 1.0.9
Summary: Defines custom datatypes for use in cycler scripts related.
Author-email: Marius Crisan <mariuscrsn+pypi@gmail.com>, Pablo Pastor <pastorpflores+pypi@gmail.com>, Javier Sanz <javiersanzmoline+pypi@gmail.com>, Roberto Aldea <r.aldea.csic+pypi@gmail.com>, Luis Roche <luis.roche@hotmail.com>
Maintainer-email: Marius Crisan <mariuscrsn+pypi@gmail.com>, Javier Sanz <javiersanzmoline+pypi@gmail.com>
License: GNU GENERAL PUBLIC LICENSE
Project-URL: Homepage, https://github.com/WattRex/Battery-Experiments-Manager/
Project-URL: Bug Reports, https://github.com/WattRex/Battery-Experiments-Manager/issues
Project-URL: Bug Tracker, https://github.com/WattRex/Battery-Experiments-Manager/issues
Project-URL: Source, https://github.com/WattRex/Battery-Experiments-Manager/tree/develop/mn_manager/src/wattrex_mn_manager
Project-URL: Funding, https://donate.pypi.org
Keywords: manager,wattrex,cycler,mqtt,broker,database
Classifier: Development Status :: 3 - Alpha
Classifier: Topic :: Software Development :: Embedded Systems
Classifier: Operating System :: OS Independent
Classifier: License :: OSI Approved :: GNU Affero General Public License v3
Classifier: Programming Language :: Python :: 3
Classifier: Programming Language :: Python :: 3.7
Classifier: Programming Language :: Python :: 3.8
Classifier: Programming Language :: Python :: 3.9
Classifier: Programming Language :: Python :: 3.10
Classifier: Programming Language :: Python :: 3.11
Classifier: Programming Language :: Python :: 3 :: Only
Requires-Python: >=3.7
License-File: LICENSE.txt
Requires-Dist: system-logger-tool
Requires-Dist: system-shared-tool
Requires-Dist: wattrex-cycler-datatypes
Requires-Dist: wattrex-driver-mqtt
Requires-Dist: wattrex-driver-db >=0.0.16
